lsrm
